calamity/__init__.py
calamity/core.py
calamity-0.1.0.dist-info/WHEEL
calamity-0.1.0.dist-info/METADATA
calamity-0.1.0.dist-info/license_files/LICENSE
calamity-0.1.0.dist-info/RECORD
