Metadata-Version: 2.1
Name: calamity
Version: 0.1.0
Summary: Remote Graia Broadcast.
License: MIT
Author-email: luxuncang <luxuncang@qq.com>
Requires-Python: >=3.9
Requires-Dist: graia-broadcast>=0.18.2
Requires-Dist: lacia>=0.0.5
